MANIFEST.in
README.md
parameters.json
setup.cfg
setup.py
phos/__init__.py
phos/app.py
phos/defaults.py
phos/pipeline.py
phos/version.py
phos/algo/__init__.py
phos/algo/activity.py
phos/algo/anat.py
phos/algo/functional_sites.py
phos/algo/logistic_regression.py
phos/algo/subnetwork.py
phos/data/__init__.py
phos/data/functional_sites.py
phos/data/network.py
phos/data/read.py
phos/data/silac.py
phos/util/__init__.py
phos/util/fdr.py
phos/util/io.py
phos/util/mapping.py
phos/util/network.py
photon_ptm.egg-info/PKG-INFO
photon_ptm.egg-info/SOURCES.txt
photon_ptm.egg-info/dependency_links.txt
photon_ptm.egg-info/requires.txt
photon_ptm.egg-info/top_level.txt