Metadata-Version: 1.0
Name: photon-ptm
Version: 0.2.8
Summary: PHOsphoproteomic dissecTiOn via Networks
Home-page: http://www.github.com/jdrudolph/photon
Author: Jan Rudolph
Author-email: jan.daniel.rudolph@gmail.com
License: MIT
Platform: UNKNOWN
